agt_lab_server-0.1.7.dist-info/licenses/LICENSE
agt_server/__init__.py
agt_server/cli.py
agt_server/core/__init__.py
agt_server/core/engine.py
agt_server/core/local_arena.py
agt_server/core/utils.py
agt_server/core/agents/__init__.py
agt_server/core/agents/test_auction_agents.py
agt_server/core/agents/common/base_agent.py
agt_server/core/agents/common/bosii_agent.py
agt_server/core/agents/common/chicken_agent.py
agt_server/core/agents/common/q_learning.py
agt_server/core/agents/common/rps_agent.py
agt_server/core/agents/lab01/compromise_agent.py
agt_server/core/agents/lab01/continue_agent.py
agt_server/core/agents/lab01/cooperate_agent.py
agt_server/core/agents/lab01/defect_agent.py
agt_server/core/agents/lab01/fictitious_play_agent.py
agt_server/core/agents/lab01/paper_agent.py
agt_server/core/agents/lab01/random_agent.py
agt_server/core/agents/lab01/random_bos_agent.py
agt_server/core/agents/lab01/random_chicken_agent.py
agt_server/core/agents/lab01/random_pd_agent.py
agt_server/core/agents/lab01/rock_agent.py
agt_server/core/agents/lab01/scissors_agent.py
agt_server/core/agents/lab01/stubborn_agent.py
agt_server/core/agents/lab01/swerve_agent.py
agt_server/core/agents/lab01/tit_for_tat_agent.py
agt_server/core/agents/lab02/bos_punitive_agent.py
agt_server/core/agents/lab02/bos_reluctant_agent.py
agt_server/core/agents/lab02/compromise_agent.py
agt_server/core/agents/lab02/random_bos_agent.py
agt_server/core/agents/lab02/stubborn_agent.py
agt_server/core/agents/lab03/continue_agent.py
agt_server/core/agents/lab03/random_chicken_agent.py
agt_server/core/agents/lab03/swerve_agent.py
agt_server/core/agents/lab04/always_stay_agent.py
agt_server/core/agents/lab04/base_lemonade_agent.py
agt_server/core/agents/lab04/random_lemonade_agent.py
agt_server/core/agents/lab04/stick_agent.py
agt_server/core/agents/lab06/base_auction_agent.py
agt_server/core/agents/lab07/__init__.py
agt_server/core/agents/lab07/aggressive_agent.py
agt_server/core/agents/lab07/conservative_agent.py
agt_lab_server-0.1.7.dist-info/METADATA
agt_lab_server-0.1.7.dist-info/WHEEL
agt_lab_server-0.1.7.dist-info/entry_points.txt
agt_lab_server-0.1.7.dist-info/top_level.txt
agt_lab_server-0.1.7.dist-info/RECORD
