Metadata-Version: 2.4
Name: agt-lab-server
Version: 0.1.7
Summary: AGT Lab Server for Game Theory Competitions - A tournament server for game theory lab competitions
Author: AGT Server Team
License: MIT
Project-URL: Homepage, https://github.com/yourusername/agt-lab-server
Project-URL: Documentation, https://agt-lab-server.readthedocs.io/
Project-URL: Repository, https://github.com/yourusername/agt-lab-server
Project-URL: Bug-Tracker, https://github.com/yourusername/agt-lab-server/issues
Classifier: Development Status :: 4 - Beta
Classifier: Intended Audience :: Education
Classifier: Intended Audience :: Science/Research
Classifier: Programming Language :: Python :: 3
Classifier: Programming Language :: Python :: 3.8
Classifier: Programming Language :: Python :: 3.9
Classifier: Programming Language :: Python :: 3.10
Classifier: Programming Language :: Python :: 3.11
Classifier: Topic :: Education
Classifier: Topic :: Games/Entertainment
Classifier: Topic :: Scientific/Engineering :: Artificial Intelligence
Requires-Python: >=3.8
License-File: LICENSE
Requires-Dist: numpy>=1.21.0
Requires-Dist: pandas>=1.3.0
Requires-Dist: pytest-asyncio
Requires-Dist: matplotlib
Requires-Dist: Flask>=2.0.0
Requires-Dist: requests>=2.25.0
Requires-Dist: psutil>=5.8.0
Requires-Dist: asyncio>=3.4.3
Requires-Dist: aiohttp>=3.8.0
Provides-Extra: dev
Requires-Dist: pytest; extra == "dev"
Requires-Dist: pytest-asyncio; extra == "dev"
Requires-Dist: black; extra == "dev"
Requires-Dist: flake8; extra == "dev"
Requires-Dist: mypy; extra == "dev"
Dynamic: license-file
Dynamic: requires-python
